// Compiled from Keys.java (version 1.8 : 52.0, super bit)
// Signature: Ljava/lang/Enum<Lorg/openqa/selenium/Keys;>;Ljava/lang/CharSequence;
public final enum org.openqa.selenium.Keys implements java.lang.CharSequence {
  
  // Field descriptor #215 Lorg/openqa/selenium/Keys;
  public static final enum org.openqa.selenium.Keys NULL;
  
  // Field descriptor #215 Lorg/openqa/selenium/Keys;
  public static final enum org.openqa.selenium.Keys CANCEL;
  
  // Field descriptor #215 Lorg/openqa/selenium/Keys;
  public static final enum org.openqa.selenium.Keys HELP;
  
  // Field descriptor #215 Lorg/openqa/selenium/Keys;
  public static final enum org.openqa.selenium.Keys BACK_SPACE;
  
  // Field descriptor #215 Lorg/openqa/selenium/Keys;
  public static final enum org.openqa.selenium.Keys TAB;
  
  // Field descriptor #215 Lorg/openqa/selenium/Keys;
  public static final enum org.openqa.selenium.Keys CLEAR;
  
  // Field descriptor #215 Lorg/openqa/selenium/Keys;
  public static final enum org.openqa.selenium.Keys RETURN;
  
  // Field descriptor #215 Lorg/openqa/selenium/Keys;
  public static final enum org.openqa.selenium.Keys ENTER;
  
  // Field descriptor #215 Lorg/openqa/selenium/Keys;
  public static final enum org.openqa.selenium.Keys SHIFT;
  
  // Field descriptor #215 Lorg/openqa/selenium/Keys;
  public static final enum org.openqa.selenium.Keys LEFT_SHIFT;
  
  // Field descriptor #215 Lorg/openqa/selenium/Keys;
  public static final enum org.openqa.selenium.Keys CONTROL;
  
  // Field descriptor #215 Lorg/openqa/selenium/Keys;
  public static final enum org.openqa.selenium.Keys LEFT_CONTROL;
  
  // Field descriptor #215 Lorg/openqa/selenium/Keys;
  public static final enum org.openqa.selenium.Keys ALT;
  
  // Field descriptor #215 Lorg/openqa/selenium/Keys;
  public static final enum org.openqa.selenium.Keys LEFT_ALT;
  
  // Field descriptor #215 Lorg/openqa/selenium/Keys;
  public static final enum org.openqa.selenium.Keys PAUSE;
  
  // Field descriptor #215 Lorg/openqa/selenium/Keys;
  public static final enum org.openqa.selenium.Keys ESCAPE;
  
  // Field descriptor #215 Lorg/openqa/selenium/Keys;
  public static final enum org.openqa.selenium.Keys SPACE;
  
  // Field descriptor #215 Lorg/openqa/selenium/Keys;
  public static final enum org.openqa.selenium.Keys PAGE_UP;
  
  // Field descriptor #215 Lorg/openqa/selenium/Keys;
  public static final enum org.openqa.selenium.Keys PAGE_DOWN;
  
  // Field descriptor #215 Lorg/openqa/selenium/Keys;
  public static final enum org.openqa.selenium.Keys END;
  
  // Field descriptor #215 Lorg/openqa/selenium/Keys;
  public static final enum org.openqa.selenium.Keys HOME;
  
  // Field descriptor #215 Lorg/openqa/selenium/Keys;
  public static final enum org.openqa.selenium.Keys LEFT;
  
  // Field descriptor #215 Lorg/openqa/selenium/Keys;
  public static final enum org.openqa.selenium.Keys ARROW_LEFT;
  
  // Field descriptor #215 Lorg/openqa/selenium/Keys;
  public static final enum org.openqa.selenium.Keys UP;
  
  // Field descriptor #215 Lorg/openqa/selenium/Keys;
  public static final enum org.openqa.selenium.Keys ARROW_UP;
  
  // Field descriptor #215 Lorg/openqa/selenium/Keys;
  public static final enum org.openqa.selenium.Keys RIGHT;
  
  // Field descriptor #215 Lorg/openqa/selenium/Keys;
  public static final enum org.openqa.selenium.Keys ARROW_RIGHT;
  
  // Field descriptor #215 Lorg/openqa/selenium/Keys;
  public static final enum org.openqa.selenium.Keys DOWN;
  
  // Field descriptor #215 Lorg/openqa/selenium/Keys;
  public static final enum org.openqa.selenium.Keys ARROW_DOWN;
  
  // Field descriptor #215 Lorg/openqa/selenium/Keys;
  public static final enum org.openqa.selenium.Keys INSERT;
  
  // Field descriptor #215 Lorg/openqa/selenium/Keys;
  public static final enum org.openqa.selenium.Keys DELETE;
  
  // Field descriptor #215 Lorg/openqa/selenium/Keys;
  public static final enum org.openqa.selenium.Keys SEMICOLON;
  
  // Field descriptor #215 Lorg/openqa/selenium/Keys;
  public static final enum org.openqa.selenium.Keys EQUALS;
  
  // Field descriptor #215 Lorg/openqa/selenium/Keys;
  public static final enum org.openqa.selenium.Keys NUMPAD0;
  
  // Field descriptor #215 Lorg/openqa/selenium/Keys;
  public static final enum org.openqa.selenium.Keys NUMPAD1;
  
  // Field descriptor #215 Lorg/openqa/selenium/Keys;
  public static final enum org.openqa.selenium.Keys NUMPAD2;
  
  // Field descriptor #215 Lorg/openqa/selenium/Keys;
  public static final enum org.openqa.selenium.Keys NUMPAD3;
  
  // Field descriptor #215 Lorg/openqa/selenium/Keys;
  public static final enum org.openqa.selenium.Keys NUMPAD4;
  
  // Field descriptor #215 Lorg/openqa/selenium/Keys;
  public static final enum org.openqa.selenium.Keys NUMPAD5;
  
  // Field descriptor #215 Lorg/openqa/selenium/Keys;
  public static final enum org.openqa.selenium.Keys NUMPAD6;
  
  // Field descriptor #215 Lorg/openqa/selenium/Keys;
  public static final enum org.openqa.selenium.Keys NUMPAD7;
  
  // Field descriptor #215 Lorg/openqa/selenium/Keys;
  public static final enum org.openqa.selenium.Keys NUMPAD8;
  
  // Field descriptor #215 Lorg/openqa/selenium/Keys;
  public static final enum org.openqa.selenium.Keys NUMPAD9;
  
  // Field descriptor #215 Lorg/openqa/selenium/Keys;
  public static final enum org.openqa.selenium.Keys MULTIPLY;
  
  // Field descriptor #215 Lorg/openqa/selenium/Keys;
  public static final enum org.openqa.selenium.Keys ADD;
  
  // Field descriptor #215 Lorg/openqa/selenium/Keys;
  public static final enum org.openqa.selenium.Keys SEPARATOR;
  
  // Field descriptor #215 Lorg/openqa/selenium/Keys;
  public static final enum org.openqa.selenium.Keys SUBTRACT;
  
  // Field descriptor #215 Lorg/openqa/selenium/Keys;
  public static final enum org.openqa.selenium.Keys DECIMAL;
  
  // Field descriptor #215 Lorg/openqa/selenium/Keys;
  public static final enum org.openqa.selenium.Keys DIVIDE;
  
  // Field descriptor #215 Lorg/openqa/selenium/Keys;
  public static final enum org.openqa.selenium.Keys F1;
  
  // Field descriptor #215 Lorg/openqa/selenium/Keys;
  public static final enum org.openqa.selenium.Keys F2;
  
  // Field descriptor #215 Lorg/openqa/selenium/Keys;
  public static final enum org.openqa.selenium.Keys F3;
  
  // Field descriptor #215 Lorg/openqa/selenium/Keys;
  public static final enum org.openqa.selenium.Keys F4;
  
  // Field descriptor #215 Lorg/openqa/selenium/Keys;
  public static final enum org.openqa.selenium.Keys F5;
  
  // Field descriptor #215 Lorg/openqa/selenium/Keys;
  public static final enum org.openqa.selenium.Keys F6;
  
  // Field descriptor #215 Lorg/openqa/selenium/Keys;
  public static final enum org.openqa.selenium.Keys F7;
  
  // Field descriptor #215 Lorg/openqa/selenium/Keys;
  public static final enum org.openqa.selenium.Keys F8;
  
  // Field descriptor #215 Lorg/openqa/selenium/Keys;
  public static final enum org.openqa.selenium.Keys F9;
  
  // Field descriptor #215 Lorg/openqa/selenium/Keys;
  public static final enum org.openqa.selenium.Keys F10;
  
  // Field descriptor #215 Lorg/openqa/selenium/Keys;
  public static final enum org.openqa.selenium.Keys F11;
  
  // Field descriptor #215 Lorg/openqa/selenium/Keys;
  public static final enum org.openqa.selenium.Keys F12;
  
  // Field descriptor #215 Lorg/openqa/selenium/Keys;
  public static final enum org.openqa.selenium.Keys META;
  
  // Field descriptor #215 Lorg/openqa/selenium/Keys;
  public static final enum org.openqa.selenium.Keys COMMAND;
  
  // Field descriptor #215 Lorg/openqa/selenium/Keys;
  public static final enum org.openqa.selenium.Keys ZENKAKU_HANKAKU;
  
  // Field descriptor #280 C
  private final char keyCode;
  
  // Field descriptor #282 I
  private final int codePoint;
  
  // Field descriptor #284 [Lorg/openqa/selenium/Keys;
  private static final synthetic org.openqa.selenium.Keys[] $VALUES;
  
  // Method descriptor #286 ()[Lorg/openqa/selenium/Keys;
  // Stack: 1, Locals: 0
  public static org.openqa.selenium.Keys[] values();
     0  getstatic org.openqa.selenium.Keys.$VALUES : org.openqa.selenium.Keys[] [1]
     3  invokevirtual org.openqa.selenium.Keys[].clone() : java.lang.Object [2]
     6  checkcast org.openqa.selenium.Keys[] [3]
     9  areturn
      Line numbers:
        [pc: 0, line: 28]
  
  // Method descriptor #290 (Ljava/lang/String;)Lorg/openqa/selenium/Keys;
  // Stack: 2, Locals: 1
  public static org.openqa.selenium.Keys valueOf(java.lang.String name);
     0  ldc <Class org.openqa.selenium.Keys> [4]
     2  aload_0 [name]
     3  invokestatic java.lang.Enum.valueOf(java.lang.Class, java.lang.String) : java.lang.Enum [5]
     6  checkcast org.openqa.selenium.Keys [4]
     9  areturn
      Line numbers:
        [pc: 0, line: 28]
      Local variable table:
        [pc: 0, pc: 10] local: name index: 0 type: java.lang.String
  
  // Method descriptor #295 (Ljava/lang/String;ILorg/openqa/selenium/Keys;)V
  // Signature: (Lorg/openqa/selenium/Keys;)V
  // Stack: 5, Locals: 4
  private Keys(java.lang.String arg0, int arg1, org.openqa.selenium.Keys key);
     0  aload_0 [this]
     1  aload_1 [arg0]
     2  iload_2 [arg1]
     3  aload_3 [key]
     4  iconst_0
     5  invokevirtual org.openqa.selenium.Keys.charAt(int) : char [6]
     8  invokespecial org.openqa.selenium.Keys(java.lang.String, int, char) [7]
    11  return
      Line numbers:
        [pc: 0, line: 105]
        [pc: 11, line: 106]
      Local variable table:
        [pc: 0, pc: 12] local: this index: 0 type: org.openqa.selenium.Keys
        [pc: 0, pc: 12] local: key index: 3 type: org.openqa.selenium.Keys
  
  // Method descriptor #300 (Ljava/lang/String;IC)V
  // Signature: (C)V
  // Stack: 3, Locals: 4
  private Keys(java.lang.String arg0, int arg1, char keyCode);
     0  aload_0 [this]
     1  aload_1 [arg0]
     2  iload_2 [arg1]
     3  invokespecial java.lang.Enum(java.lang.String, int) [8]
     6  aload_0 [this]
     7  iload_3 [keyCode]
     8  putfield org.openqa.selenium.Keys.keyCode : char [9]
    11  aload_0 [this]
    12  iload_3 [keyCode]
    13  invokestatic java.lang.String.valueOf(char) : java.lang.String [10]
    16  invokevirtual java.lang.String.codePoints() : java.util.stream.IntStream [11]
    19  invokeinterface java.util.stream.IntStream.findFirst() : java.util.OptionalInt [12] [nargs: 1]
    24  invokevirtual java.util.OptionalInt.getAsInt() : int [13]
    27  putfield org.openqa.selenium.Keys.codePoint : int [14]
    30  return
      Line numbers:
        [pc: 0, line: 108]
        [pc: 6, line: 109]
        [pc: 11, line: 110]
        [pc: 30, line: 111]
      Local variable table:
        [pc: 0, pc: 31] local: this index: 0 type: org.openqa.selenium.Keys
        [pc: 0, pc: 31] local: keyCode index: 3 type: char
  
  // Method descriptor #303 ()I
  // Stack: 1, Locals: 1
  public int getCodePoint();
    0  aload_0 [this]
    1  getfield org.openqa.selenium.Keys.codePoint : int [14]
    4  ireturn
      Line numbers:
        [pc: 0, line: 114]
      Local variable table:
        [pc: 0, pc: 5] local: this index: 0 type: org.openqa.selenium.Keys
  
  // Method descriptor #305 (I)C
  // Stack: 1, Locals: 2
  public char charAt(int index);
     0  iload_1 [index]
     1  ifne 9
     4  aload_0 [this]
     5  getfield org.openqa.selenium.Keys.keyCode : char [9]
     8  ireturn
     9  iconst_0
    10  ireturn
      Line numbers:
        [pc: 0, line: 118]
        [pc: 4, line: 119]
        [pc: 9, line: 122]
      Local variable table:
        [pc: 0, pc: 11] local: this index: 0 type: org.openqa.selenium.Keys
        [pc: 0, pc: 11] local: index index: 1 type: int
      Stack map table: number of frames 1
        [pc: 9, same]
  
  // Method descriptor #303 ()I
  // Stack: 1, Locals: 1
  public int length();
    0  iconst_1
    1  ireturn
      Line numbers:
        [pc: 0, line: 126]
      Local variable table:
        [pc: 0, pc: 2] local: this index: 0 type: org.openqa.selenium.Keys
  
  // Method descriptor #310 (II)Ljava/lang/CharSequence;
  // Stack: 2, Locals: 3
  public java.lang.CharSequence subSequence(int start, int end);
     0  iload_1 [start]
     1  ifne 17
     4  iload_2 [end]
     5  iconst_1
     6  if_icmpne 17
     9  aload_0 [this]
    10  getfield org.openqa.selenium.Keys.keyCode : char [9]
    13  invokestatic java.lang.String.valueOf(char) : java.lang.String [10]
    16  areturn
    17  new java.lang.IndexOutOfBoundsException [15]
    20  dup
    21  invokespecial java.lang.IndexOutOfBoundsException() [16]
    24  athrow
      Line numbers:
        [pc: 0, line: 130]
        [pc: 9, line: 131]
        [pc: 17, line: 134]
      Local variable table:
        [pc: 0, pc: 25] local: this index: 0 type: org.openqa.selenium.Keys
        [pc: 0, pc: 25] local: start index: 1 type: int
        [pc: 0, pc: 25] local: end index: 2 type: int
      Stack map table: number of frames 1
        [pc: 17, same]
  
  // Method descriptor #314 ()Ljava/lang/String;
  // Stack: 1, Locals: 1
  public java.lang.String toString();
    0  aload_0 [this]
    1  getfield org.openqa.selenium.Keys.keyCode : char [9]
    4  invokestatic java.lang.String.valueOf(char) : java.lang.String [10]
    7  areturn
      Line numbers:
        [pc: 0, line: 139]
      Local variable table:
        [pc: 0, pc: 8] local: this index: 0 type: org.openqa.selenium.Keys
  
  // Method descriptor #316 ([Ljava/lang/CharSequence;)Ljava/lang/String;
  // Stack: 1, Locals: 1
  public static java.lang.String chord(java.lang.CharSequence... value);
    0  aload_0 [value]
    1  invokestatic java.util.Arrays.asList(java.lang.Object[]) : java.util.List [17]
    4  invokestatic org.openqa.selenium.Keys.chord(java.lang.Iterable) : java.lang.String [18]
    7  areturn
      Line numbers:
        [pc: 0, line: 156]
      Local variable table:
        [pc: 0, pc: 8] local: value index: 0 type: java.lang.CharSequence[]
  
  // Method descriptor #319 (Ljava/lang/Iterable;)Ljava/lang/String;
  // Signature: (Ljava/lang/Iterable<Ljava/lang/CharSequence;>;)Ljava/lang/String;
  // Stack: 2, Locals: 4
  public static java.lang.String chord(java.lang.Iterable value);
     0  new java.lang.StringBuilder [19]
     3  dup
     4  invokespecial java.lang.StringBuilder() [20]
     7  astore_1 [builder]
     8  aload_0 [value]
     9  invokeinterface java.lang.Iterable.iterator() : java.util.Iterator [21] [nargs: 1]
    14  astore_2
    15  aload_2
    16  invokeinterface java.util.Iterator.hasNext() : boolean [22] [nargs: 1]
    21  ifeq 43
    24  aload_2
    25  invokeinterface java.util.Iterator.next() : java.lang.Object [23] [nargs: 1]
    30  checkcast java.lang.CharSequence [24]
    33  astore_3 [seq]
    34  aload_1 [builder]
    35  aload_3 [seq]
    36  invokevirtual java.lang.StringBuilder.append(java.lang.CharSequence) : java.lang.StringBuilder [25]
    39  pop
    40  goto 15
    43  aload_1 [builder]
    44  getstatic org.openqa.selenium.Keys.NULL : org.openqa.selenium.Keys [26]
    47  invokevirtual java.lang.StringBuilder.append(java.lang.CharSequence) : java.lang.StringBuilder [25]
    50  pop
    51  aload_1 [builder]
    52  invokevirtual java.lang.StringBuilder.toString() : java.lang.String [27]
    55  areturn
      Line numbers:
        [pc: 0, line: 165]
        [pc: 8, line: 167]
        [pc: 34, line: 168]
        [pc: 40, line: 169]
        [pc: 43, line: 171]
        [pc: 51, line: 172]
      Local variable table:
        [pc: 34, pc: 40] local: seq index: 3 type: java.lang.CharSequence
        [pc: 0, pc: 56] local: value index: 0 type: java.lang.Iterable
        [pc: 8, pc: 56] local: builder index: 1 type: java.lang.StringBuilder
      Local variable type table:
        [pc: 0, pc: 56] local: value index: 0 type: java.lang.Iterable<java.lang.CharSequence>
      Stack map table: number of frames 2
        [pc: 15, append: {java.lang.StringBuilder, java.util.Iterator}]
        [pc: 43, chop 1 local(s)]
  
  // Method descriptor #331 (C)Lorg/openqa/selenium/Keys;
  // Stack: 2, Locals: 5
  public static org.openqa.selenium.Keys getKeyFromUnicode(char key);
     0  invokestatic org.openqa.selenium.Keys.values() : org.openqa.selenium.Keys[] [28]
     3  astore_1
     4  aload_1
     5  arraylength
     6  istore_2
     7  iconst_0
     8  istore_3
     9  iload_3
    10  iload_2
    11  if_icmpge 38
    14  aload_1
    15  iload_3
    16  aaload
    17  astore 4 [unicodeKey]
    19  aload 4 [unicodeKey]
    21  iconst_0
    22  invokevirtual org.openqa.selenium.Keys.charAt(int) : char [6]
    25  iload_0 [key]
    26  if_icmpne 32
    29  aload 4 [unicodeKey]
    31  areturn
    32  iinc 3 1
    35  goto 9
    38  aconst_null
    39  areturn
      Line numbers:
        [pc: 0, line: 183]
        [pc: 19, line: 184]
        [pc: 29, line: 185]
        [pc: 32, line: 183]
        [pc: 38, line: 189]
      Local variable table:
        [pc: 19, pc: 32] local: unicodeKey index: 4 type: org.openqa.selenium.Keys
        [pc: 0, pc: 40] local: key index: 0 type: char
      Stack map table: number of frames 3
        [pc: 9, append: {org.openqa.selenium.Keys[], int, int}]
        [pc: 32, same]
        [pc: 38, chop 3 local(s)]
  
  // Method descriptor #334 ()V
  // Stack: 5, Locals: 0
  static {};
       0  new org.openqa.selenium.Keys [4]
       3  dup
       4  ldc <String "NULL"> [29]
       6  iconst_0
       7  ldc <Integer 57344> [30]
       9  invokespecial org.openqa.selenium.Keys(java.lang.String, int, char) [7]
      12  putstatic org.openqa.selenium.Keys.NULL : org.openqa.selenium.Keys [26]
      15  new org.openqa.selenium.Keys [4]
      18  dup
      19  ldc <String "CANCEL"> [31]
      21  iconst_1
      22  ldc <Integer 57345> [32]
      24  invokespecial org.openqa.selenium.Keys(java.lang.String, int, char) [7]
      27  putstatic org.openqa.selenium.Keys.CANCEL : org.openqa.selenium.Keys [33]
      30  new org.openqa.selenium.Keys [4]
      33  dup
      34  ldc <String "HELP"> [34]
      36  iconst_2
      37  ldc <Integer 57346> [35]
      39  invokespecial org.openqa.selenium.Keys(java.lang.String, int, char) [7]
      42  putstatic org.openqa.selenium.Keys.HELP : org.openqa.selenium.Keys [36]
      45  new org.openqa.selenium.Keys [4]
      48  dup
      49  ldc <String "BACK_SPACE"> [37]
      51  iconst_3
      52  ldc <Integer 57347> [38]
      54  invokespecial org.openqa.selenium.Keys(java.lang.String, int, char) [7]
      57  putstatic org.openqa.selenium.Keys.BACK_SPACE : org.openqa.selenium.Keys [39]
      60  new org.openqa.selenium.Keys [4]
      63  dup
      64  ldc <String "TAB"> [40]
      66  iconst_4
      67  ldc <Integer 57348> [41]
      69  invokespecial org.openqa.selenium.Keys(java.lang.String, int, char) [7]
      72  putstatic org.openqa.selenium.Keys.TAB : org.openqa.selenium.Keys [42]
      75  new org.openqa.selenium.Keys [4]
      78  dup
      79  ldc <String "CLEAR"> [43]
      81  iconst_5
      82  ldc <Integer 57349> [44]
      84  invokespecial org.openqa.selenium.Keys(java.lang.String, int, char) [7]
      87  putstatic org.openqa.selenium.Keys.CLEAR : org.openqa.selenium.Keys [45]
      90  new org.openqa.selenium.Keys [4]
      93  dup
      94  ldc <String "RETURN"> [46]
      96  bipush 6
      98  ldc <Integer 57350> [47]
     100  invokespecial org.openqa.selenium.Keys(java.lang.String, int, char) [7]
     103  putstatic org.openqa.selenium.Keys.RETURN : org.openqa.selenium.Keys [48]
     106  new org.openqa.selenium.Keys [4]
     109  dup
     110  ldc <String "ENTER"> [49]
     112  bipush 7
     114  ldc <Integer 57351> [50]
     116  invokespecial org.openqa.selenium.Keys(java.lang.String, int, char) [7]
     119  putstatic org.openqa.selenium.Keys.ENTER : org.openqa.selenium.Keys [51]
     122  new org.openqa.selenium.Keys [4]
     125  dup
     126  ldc <String "SHIFT"> [52]
     128  bipush 8
     130  ldc <Integer 57352> [53]
     132  invokespecial org.openqa.selenium.Keys(java.lang.String, int, char) [7]
     135  putstatic org.openqa.selenium.Keys.SHIFT : org.openqa.selenium.Keys [54]
     138  new org.openqa.selenium.Keys [4]
     141  dup
     142  ldc <String "LEFT_SHIFT"> [55]
     144  bipush 9
     146  getstatic org.openqa.selenium.Keys.SHIFT : org.openqa.selenium.Keys [54]
     149  invokespecial org.openqa.selenium.Keys(java.lang.String, int, org.openqa.selenium.Keys) [56]
     152  putstatic org.openqa.selenium.Keys.LEFT_SHIFT : org.openqa.selenium.Keys [57]
     155  new org.openqa.selenium.Keys [4]
     158  dup
     159  ldc <String "CONTROL"> [58]
     161  bipush 10
     163  ldc <Integer 57353> [59]
     165  invokespecial org.openqa.selenium.Keys(java.lang.String, int, char) [7]
     168  putstatic org.openqa.selenium.Keys.CONTROL : org.openqa.selenium.Keys [60]
     171  new org.openqa.selenium.Keys [4]
     174  dup
     175  ldc <String "LEFT_CONTROL"> [61]
     177  bipush 11
     179  getstatic org.openqa.selenium.Keys.CONTROL : org.openqa.selenium.Keys [60]
     182  invokespecial org.openqa.selenium.Keys(java.lang.String, int, org.openqa.selenium.Keys) [56]
     185  putstatic org.openqa.selenium.Keys.LEFT_CONTROL : org.openqa.selenium.Keys [62]
     188  new org.openqa.selenium.Keys [4]
     191  dup
     192  ldc <String "ALT"> [63]
     194  bipush 12
     196  ldc <Integer 57354> [64]
     198  invokespecial org.openqa.selenium.Keys(java.lang.String, int, char) [7]
     201  putstatic org.openqa.selenium.Keys.ALT : org.openqa.selenium.Keys [65]
     204  new org.openqa.selenium.Keys [4]
     207  dup
     208  ldc <String "LEFT_ALT"> [66]
     210  bipush 13
     212  getstatic org.openqa.selenium.Keys.ALT : org.openqa.selenium.Keys [65]
     215  invokespecial org.openqa.selenium.Keys(java.lang.String, int, org.openqa.selenium.Keys) [56]
     218  putstatic org.openqa.selenium.Keys.LEFT_ALT : org.openqa.selenium.Keys [67]
     221  new org.openqa.selenium.Keys [4]
     224  dup
     225  ldc <String "PAUSE"> [68]
     227  bipush 14
     229  ldc <Integer 57355> [69]
     231  invokespecial org.openqa.selenium.Keys(java.lang.String, int, char) [7]
     234  putstatic org.openqa.selenium.Keys.PAUSE : org.openqa.selenium.Keys [70]
     237  new org.openqa.selenium.Keys [4]
     240  dup
     241  ldc <String "ESCAPE"> [71]
     243  bipush 15
     245  ldc <Integer 57356> [72]
     247  invokespecial org.openqa.selenium.Keys(java.lang.String, int, char) [7]
     250  putstatic org.openqa.selenium.Keys.ESCAPE : org.openqa.selenium.Keys [73]
     253  new org.openqa.selenium.Keys [4]
     256  dup
     257  ldc <String "SPACE"> [74]
     259  bipush 16
     261  ldc <Integer 57357> [75]
     263  invokespecial org.openqa.selenium.Keys(java.lang.String, int, char) [7]
     266  putstatic org.openqa.selenium.Keys.SPACE : org.openqa.selenium.Keys [76]
     269  new org.openqa.selenium.Keys [4]
     272  dup
     273  ldc <String "PAGE_UP"> [77]
     275  bipush 17
     277  ldc <Integer 57358> [78]
     279  invokespecial org.openqa.selenium.Keys(java.lang.String, int, char) [7]
     282  putstatic org.openqa.selenium.Keys.PAGE_UP : org.openqa.selenium.Keys [79]
     285  new org.openqa.selenium.Keys [4]
     288  dup
     289  ldc <String "PAGE_DOWN"> [80]
     291  bipush 18
     293  ldc <Integer 57359> [81]
     295  invokespecial org.openqa.selenium.Keys(java.lang.String, int, char) [7]
     298  putstatic org.openqa.selenium.Keys.PAGE_DOWN : org.openqa.selenium.Keys [82]
     301  new org.openqa.selenium.Keys [4]
     304  dup
     305  ldc <String "END"> [83]
     307  bipush 19
     309  ldc <Integer 57360> [84]
     311  invokespecial org.openqa.selenium.Keys(java.lang.String, int, char) [7]
     314  putstatic org.openqa.selenium.Keys.END : org.openqa.selenium.Keys [85]
     317  new org.openqa.selenium.Keys [4]
     320  dup
     321  ldc <String "HOME"> [86]
     323  bipush 20
     325  ldc <Integer 57361> [87]
     327  invokespecial org.openqa.selenium.Keys(java.lang.String, int, char) [7]
     330  putstatic org.openqa.selenium.Keys.HOME : org.openqa.selenium.Keys [88]
     333  new org.openqa.selenium.Keys [4]
     336  dup
     337  ldc <String "LEFT"> [89]
     339  bipush 21
     341  ldc <Integer 57362> [90]
     343  invokespecial org.openqa.selenium.Keys(java.lang.String, int, char) [7]
     346  putstatic org.openqa.selenium.Keys.LEFT : org.openqa.selenium.Keys [91]
     349  new org.openqa.selenium.Keys [4]
     352  dup
     353  ldc <String "ARROW_LEFT"> [92]
     355  bipush 22
     357  getstatic org.openqa.selenium.Keys.LEFT : org.openqa.selenium.Keys [91]
     360  invokespecial org.openqa.selenium.Keys(java.lang.String, int, org.openqa.selenium.Keys) [56]
     363  putstatic org.openqa.selenium.Keys.ARROW_LEFT : org.openqa.selenium.Keys [93]
     366  new org.openqa.selenium.Keys [4]
     369  dup
     370  ldc <String "UP"> [94]
     372  bipush 23
     374  ldc <Integer 57363> [95]
     376  invokespecial org.openqa.selenium.Keys(java.lang.String, int, char) [7]
     379  putstatic org.openqa.selenium.Keys.UP : org.openqa.selenium.Keys [96]
     382  new org.openqa.selenium.Keys [4]
     385  dup
     386  ldc <String "ARROW_UP"> [97]
     388  bipush 24
     390  getstatic org.openqa.selenium.Keys.UP : org.openqa.selenium.Keys [96]
     393  invokespecial org.openqa.selenium.Keys(java.lang.String, int, org.openqa.selenium.Keys) [56]
     396  putstatic org.openqa.selenium.Keys.ARROW_UP : org.openqa.selenium.Keys [98]
     399  new org.openqa.selenium.Keys [4]
     402  dup
     403  ldc <String "RIGHT"> [99]
     405  bipush 25
     407  ldc <Integer 57364> [100]
     409  invokespecial org.openqa.selenium.Keys(java.lang.String, int, char) [7]
     412  putstatic org.openqa.selenium.Keys.RIGHT : org.openqa.selenium.Keys [101]
     415  new org.openqa.selenium.Keys [4]
     418  dup
     419  ldc <String "ARROW_RIGHT"> [102]
     421  bipush 26
     423  getstatic org.openqa.selenium.Keys.RIGHT : org.openqa.selenium.Keys [101]
     426  invokespecial org.openqa.selenium.Keys(java.lang.String, int, org.openqa.selenium.Keys) [56]
     429  putstatic org.openqa.selenium.Keys.ARROW_RIGHT : org.openqa.selenium.Keys [103]
     432  new org.openqa.selenium.Keys [4]
     435  dup
     436  ldc <String "DOWN"> [104]
     438  bipush 27
     440  ldc <Integer 57365> [105]
     442  invokespecial org.openqa.selenium.Keys(java.lang.String, int, char) [7]
     445  putstatic org.openqa.selenium.Keys.DOWN : org.openqa.selenium.Keys [106]
     448  new org.openqa.selenium.Keys [4]
     451  dup
     452  ldc <String "ARROW_DOWN"> [107]
     454  bipush 28
     456  getstatic org.openqa.selenium.Keys.DOWN : org.openqa.selenium.Keys [106]
     459  invokespecial org.openqa.selenium.Keys(java.lang.String, int, org.openqa.selenium.Keys) [56]
     462  putstatic org.openqa.selenium.Keys.ARROW_DOWN : org.openqa.selenium.Keys [108]
     465  new org.openqa.selenium.Keys [4]
     468  dup
     469  ldc <String "INSERT"> [109]
     471  bipush 29
     473  ldc <Integer 57366> [110]
     475  invokespecial org.openqa.selenium.Keys(java.lang.String, int, char) [7]
     478  putstatic org.openqa.selenium.Keys.INSERT : org.openqa.selenium.Keys [111]
     481  new org.openqa.selenium.Keys [4]
     484  dup
     485  ldc <String "DELETE"> [112]
     487  bipush 30
     489  ldc <Integer 57367> [113]
     491  invokespecial org.openqa.selenium.Keys(java.lang.String, int, char) [7]
     494  putstatic org.openqa.selenium.Keys.DELETE : org.openqa.selenium.Keys [114]
     497  new org.openqa.selenium.Keys [4]
     500  dup
     501  ldc <String "SEMICOLON"> [115]
     503  bipush 31
     505  ldc <Integer 57368> [116]
     507  invokespecial org.openqa.selenium.Keys(java.lang.String, int, char) [7]
     510  putstatic org.openqa.selenium.Keys.SEMICOLON : org.openqa.selenium.Keys [117]
     513  new org.openqa.selenium.Keys [4]
     516  dup
     517  ldc <String "EQUALS"> [118]
     519  bipush 32
     521  ldc <Integer 57369> [119]
     523  invokespecial org.openqa.selenium.Keys(java.lang.String, int, char) [7]
     526  putstatic org.openqa.selenium.Keys.EQUALS : org.openqa.selenium.Keys [120]
     529  new org.openqa.selenium.Keys [4]
     532  dup
     533  ldc <String "NUMPAD0"> [121]
     535  bipush 33
     537  ldc <Integer 57370> [122]
     539  invokespecial org.openqa.selenium.Keys(java.lang.String, int, char) [7]
     542  putstatic org.openqa.selenium.Keys.NUMPAD0 : org.openqa.selenium.Keys [123]
     545  new org.openqa.selenium.Keys [4]
     548  dup
     549  ldc <String "NUMPAD1"> [124]
     551  bipush 34
     553  ldc <Integer 57371> [125]
     555  invokespecial org.openqa.selenium.Keys(java.lang.String, int, char) [7]
     558  putstatic org.openqa.selenium.Keys.NUMPAD1 : org.openqa.selenium.Keys [126]
     561  new org.openqa.selenium.Keys [4]
     564  dup
     565  ldc <String "NUMPAD2"> [127]
     567  bipush 35
     569  ldc <Integer 57372> [128]
     571  invokespecial org.openqa.selenium.Keys(java.lang.String, int, char) [7]
     574  putstatic org.openqa.selenium.Keys.NUMPAD2 : org.openqa.selenium.Keys [129]
     577  new org.openqa.selenium.Keys [4]
     580  dup
     581  ldc <String "NUMPAD3"> [130]
     583  bipush 36
     585  ldc <Integer 57373> [131]
     587  invokespecial org.openqa.selenium.Keys(java.lang.String, int, char) [7]
     590  putstatic org.openqa.selenium.Keys.NUMPAD3 : org.openqa.selenium.Keys [132]
     593  new org.openqa.selenium.Keys [4]
     596  dup
     597  ldc <String "NUMPAD4"> [133]
     599  bipush 37
     601  ldc <Integer 57374> [134]
     603  invokespecial org.openqa.selenium.Keys(java.lang.String, int, char) [7]
     606  putstatic org.openqa.selenium.Keys.NUMPAD4 : org.openqa.selenium.Keys [135]
     609  new org.openqa.selenium.Keys [4]
     612  dup
     613  ldc <String "NUMPAD5"> [136]
     615  bipush 38
     617  ldc <Integer 57375> [137]
     619  invokespecial org.openqa.selenium.Keys(java.lang.String, int, char) [7]
     622  putstatic org.openqa.selenium.Keys.NUMPAD5 : org.openqa.selenium.Keys [138]
     625  new org.openqa.selenium.Keys [4]
     628  dup
     629  ldc <String "NUMPAD6"> [139]
     631  bipush 39
     633  ldc <Integer 57376> [140]
     635  invokespecial org.openqa.selenium.Keys(java.lang.String, int, char) [7]
     638  putstatic org.openqa.selenium.Keys.NUMPAD6 : org.openqa.selenium.Keys [141]
     641  new org.openqa.selenium.Keys [4]
     644  dup
     645  ldc <String "NUMPAD7"> [142]
     647  bipush 40
     649  ldc <Integer 57377> [143]
     651  invokespecial org.openqa.selenium.Keys(java.lang.String, int, char) [7]
     654  putstatic org.openqa.selenium.Keys.NUMPAD7 : org.openqa.selenium.Keys [144]
     657  new org.openqa.selenium.Keys [4]
     660  dup
     661  ldc <String "NUMPAD8"> [145]
     663  bipush 41
     665  ldc <Integer 57378> [146]
     667  invokespecial org.openqa.selenium.Keys(java.lang.String, int, char) [7]
     670  putstatic org.openqa.selenium.Keys.NUMPAD8 : org.openqa.selenium.Keys [147]
     673  new org.openqa.selenium.Keys [4]
     676  dup
     677  ldc <String "NUMPAD9"> [148]
     679  bipush 42
     681  ldc <Integer 57379> [149]
     683  invokespecial org.openqa.selenium.Keys(java.lang.String, int, char) [7]
     686  putstatic org.openqa.selenium.Keys.NUMPAD9 : org.openqa.selenium.Keys [150]
     689  new org.openqa.selenium.Keys [4]
     692  dup
     693  ldc <String "MULTIPLY"> [151]
     695  bipush 43
     697  ldc <Integer 57380> [152]
     699  invokespecial org.openqa.selenium.Keys(java.lang.String, int, char) [7]
     702  putstatic org.openqa.selenium.Keys.MULTIPLY : org.openqa.selenium.Keys [153]
     705  new org.openqa.selenium.Keys [4]
     708  dup
     709  ldc <String "ADD"> [154]
     711  bipush 44
     713  ldc <Integer 57381> [155]
     715  invokespecial org.openqa.selenium.Keys(java.lang.String, int, char) [7]
     718  putstatic org.openqa.selenium.Keys.ADD : org.openqa.selenium.Keys [156]
     721  new org.openqa.selenium.Keys [4]
     724  dup
     725  ldc <String "SEPARATOR"> [157]
     727  bipush 45
     729  ldc <Integer 57382> [158]
     731  invokespecial org.openqa.selenium.Keys(java.lang.String, int, char) [7]
     734  putstatic org.openqa.selenium.Keys.SEPARATOR : org.openqa.selenium.Keys [159]
     737  new org.openqa.selenium.Keys [4]
     740  dup
     741  ldc <String "SUBTRACT"> [160]
     743  bipush 46
     745  ldc <Integer 57383> [161]
     747  invokespecial org.openqa.selenium.Keys(java.lang.String, int, char) [7]
     750  putstatic org.openqa.selenium.Keys.SUBTRACT : org.openqa.selenium.Keys [162]
     753  new org.openqa.selenium.Keys [4]
     756  dup
     757  ldc <String "DECIMAL"> [163]
     759  bipush 47
     761  ldc <Integer 57384> [164]
     763  invokespecial org.openqa.selenium.Keys(java.lang.String, int, char) [7]
     766  putstatic org.openqa.selenium.Keys.DECIMAL : org.openqa.selenium.Keys [165]
     769  new org.openqa.selenium.Keys [4]
     772  dup
     773  ldc <String "DIVIDE"> [166]
     775  bipush 48
     777  ldc <Integer 57385> [167]
     779  invokespecial org.openqa.selenium.Keys(java.lang.String, int, char) [7]
     782  putstatic org.openqa.selenium.Keys.DIVIDE : org.openqa.selenium.Keys [168]
     785  new org.openqa.selenium.Keys [4]
     788  dup
     789  ldc <String "F1"> [169]
     791  bipush 49
     793  ldc <Integer 57393> [170]
     795  invokespecial org.openqa.selenium.Keys(java.lang.String, int, char) [7]
     798  putstatic org.openqa.selenium.Keys.F1 : org.openqa.selenium.Keys [171]
     801  new org.openqa.selenium.Keys [4]
     804  dup
     805  ldc <String "F2"> [172]
     807  bipush 50
     809  ldc <Integer 57394> [173]
     811  invokespecial org.openqa.selenium.Keys(java.lang.String, int, char) [7]
     814  putstatic org.openqa.selenium.Keys.F2 : org.openqa.selenium.Keys [174]
     817  new org.openqa.selenium.Keys [4]
     820  dup
     821  ldc <String "F3"> [175]
     823  bipush 51
     825  ldc <Integer 57395> [176]
     827  invokespecial org.openqa.selenium.Keys(java.lang.String, int, char) [7]
     830  putstatic org.openqa.selenium.Keys.F3 : org.openqa.selenium.Keys [177]
     833  new org.openqa.selenium.Keys [4]
     836  dup
     837  ldc <String "F4"> [178]
     839  bipush 52
     841  ldc <Integer 57396> [179]
     843  invokespecial org.openqa.selenium.Keys(java.lang.String, int, char) [7]
     846  putstatic org.openqa.selenium.Keys.F4 : org.openqa.selenium.Keys [180]
     849  new org.openqa.selenium.Keys [4]
     852  dup
     853  ldc <String "F5"> [181]
     855  bipush 53
     857  ldc <Integer 57397> [182]
     859  invokespecial org.openqa.selenium.Keys(java.lang.String, int, char) [7]
     862  putstatic org.openqa.selenium.Keys.F5 : org.openqa.selenium.Keys [183]
     865  new org.openqa.selenium.Keys [4]
     868  dup
     869  ldc <String "F6"> [184]
     871  bipush 54
     873  ldc <Integer 57398> [185]
     875  invokespecial org.openqa.selenium.Keys(java.lang.String, int, char) [7]
     878  putstatic org.openqa.selenium.Keys.F6 : org.openqa.selenium.Keys [186]
     881  new org.openqa.selenium.Keys [4]
     884  dup
     885  ldc <String "F7"> [187]
     887  bipush 55
     889  ldc <Integer 57399> [188]
     891  invokespecial org.openqa.selenium.Keys(java.lang.String, int, char) [7]
     894  putstatic org.openqa.selenium.Keys.F7 : org.openqa.selenium.Keys [189]
     897  new org.openqa.selenium.Keys [4]
     900  dup
     901  ldc <String "F8"> [190]
     903  bipush 56
     905  ldc <Integer 57400> [191]
     907  invokespecial org.openqa.selenium.Keys(java.lang.String, int, char) [7]
     910  putstatic org.openqa.selenium.Keys.F8 : org.openqa.selenium.Keys [192]
     913  new org.openqa.selenium.Keys [4]
     916  dup
     917  ldc <String "F9"> [193]
     919  bipush 57
     921  ldc <Integer 57401> [194]
     923  invokespecial org.openqa.selenium.Keys(java.lang.String, int, char) [7]
     926  putstatic org.openqa.selenium.Keys.F9 : org.openqa.selenium.Keys [195]
     929  new org.openqa.selenium.Keys [4]
     932  dup
     933  ldc <String "F10"> [196]
     935  bipush 58
     937  ldc <Integer 57402> [197]
     939  invokespecial org.openqa.selenium.Keys(java.lang.String, int, char) [7]
     942  putstatic org.openqa.selenium.Keys.F10 : org.openqa.selenium.Keys [198]
     945  new org.openqa.selenium.Keys [4]
     948  dup
     949  ldc <String "F11"> [199]
     951  bipush 59
     953  ldc <Integer 57403> [200]
     955  invokespecial org.openqa.selenium.Keys(java.lang.String, int, char) [7]
     958  putstatic org.openqa.selenium.Keys.F11 : org.openqa.selenium.Keys [201]
     961  new org.openqa.selenium.Keys [4]
     964  dup
     965  ldc <String "F12"> [202]
     967  bipush 60
     969  ldc <Integer 57404> [203]
     971  invokespecial org.openqa.selenium.Keys(java.lang.String, int, char) [7]
     974  putstatic org.openqa.selenium.Keys.F12 : org.openqa.selenium.Keys [204]
     977  new org.openqa.selenium.Keys [4]
     980  dup
     981  ldc <String "META"> [205]
     983  bipush 61
     985  ldc <Integer 57405> [206]
     987  invokespecial org.openqa.selenium.Keys(java.lang.String, int, char) [7]
     990  putstatic org.openqa.selenium.Keys.META : org.openqa.selenium.Keys [207]
     993  new org.openqa.selenium.Keys [4]
     996  dup
     997  ldc <String "COMMAND"> [208]
     999  bipush 62
    1001  getstatic org.openqa.selenium.Keys.META : org.openqa.selenium.Keys [207]
    1004  invokespecial org.openqa.selenium.Keys(java.lang.String, int, org.openqa.selenium.Keys) [56]
    1007  putstatic org.openqa.selenium.Keys.COMMAND : org.openqa.selenium.Keys [209]
    1010  new org.openqa.selenium.Keys [4]
    1013  dup
    1014  ldc <String "ZENKAKU_HANKAKU"> [210]
    1016  bipush 63
    1018  ldc <Integer 57408> [211]
    1020  invokespecial org.openqa.selenium.Keys(java.lang.String, int, char) [7]
    1023  putstatic org.openqa.selenium.Keys.ZENKAKU_HANKAKU : org.openqa.selenium.Keys [212]
    1026  bipush 64
    1028  anewarray org.openqa.selenium.Keys [4]
    1031  dup
    1032  iconst_0
    1033  getstatic org.openqa.selenium.Keys.NULL : org.openqa.selenium.Keys [26]
    1036  aastore
    1037  dup
    1038  iconst_1
    1039  getstatic org.openqa.selenium.Keys.CANCEL : org.openqa.selenium.Keys [33]
    1042  aastore
    1043  dup
    1044  iconst_2
    1045  getstatic org.openqa.selenium.Keys.HELP : org.openqa.selenium.Keys [36]
    1048  aastore
    1049  dup
    1050  iconst_3
    1051  getstatic org.openqa.selenium.Keys.BACK_SPACE : org.openqa.selenium.Keys [39]
    1054  aastore
    1055  dup
    1056  iconst_4
    1057  getstatic org.openqa.selenium.Keys.TAB : org.openqa.selenium.Keys [42]
    1060  aastore
    1061  dup
    1062  iconst_5
    1063  getstatic org.openqa.selenium.Keys.CLEAR : org.openqa.selenium.Keys [45]
    1066  aastore
    1067  dup
    1068  bipush 6
    1070  getstatic org.openqa.selenium.Keys.RETURN : org.openqa.selenium.Keys [48]
    1073  aastore
    1074  dup
    1075  bipush 7
    1077  getstatic org.openqa.selenium.Keys.ENTER : org.openqa.selenium.Keys [51]
    1080  aastore
    1081  dup
    1082  bipush 8
    1084  getstatic org.openqa.selenium.Keys.SHIFT : org.openqa.selenium.Keys [54]
    1087  aastore
    1088  dup
    1089  bipush 9
    1091  getstatic org.openqa.selenium.Keys.LEFT_SHIFT : org.openqa.selenium.Keys [57]
    1094  aastore
    1095  dup
    1096  bipush 10
    1098  getstatic org.openqa.selenium.Keys.CONTROL : org.openqa.selenium.Keys [60]
    1101  aastore
    1102  dup
    1103  bipush 11
    1105  getstatic org.openqa.selenium.Keys.LEFT_CONTROL : org.openqa.selenium.Keys [62]
    1108  aastore
    1109  dup
    1110  bipush 12
    1112  getstatic org.openqa.selenium.Keys.ALT : org.openqa.selenium.Keys [65]
    1115  aastore
    1116  dup
    1117  bipush 13
    1119  getstatic org.openqa.selenium.Keys.LEFT_ALT : org.openqa.selenium.Keys [67]
    1122  aastore
    1123  dup
    1124  bipush 14
    1126  getstatic org.openqa.selenium.Keys.PAUSE : org.openqa.selenium.Keys [70]
    1129  aastore
    1130  dup
    1131  bipush 15
    1133  getstatic org.openqa.selenium.Keys.ESCAPE : org.openqa.selenium.Keys [73]
    1136  aastore
    1137  dup
    1138  bipush 16
    1140  getstatic org.openqa.selenium.Keys.SPACE : org.openqa.selenium.Keys [76]
    1143  aastore
    1144  dup
    1145  bipush 17
    1147  getstatic org.openqa.selenium.Keys.PAGE_UP : org.openqa.selenium.Keys [79]
    1150  aastore
    1151  dup
    1152  bipush 18
    1154  getstatic org.openqa.selenium.Keys.PAGE_DOWN : org.openqa.selenium.Keys [82]
    1157  aastore
    1158  dup
    1159  bipush 19
    1161  getstatic org.openqa.selenium.Keys.END : org.openqa.selenium.Keys [85]
    1164  aastore
    1165  dup
    1166  bipush 20
    1168  getstatic org.openqa.selenium.Keys.HOME : org.openqa.selenium.Keys [88]
    1171  aastore
    1172  dup
    1173  bipush 21
    1175  getstatic org.openqa.selenium.Keys.LEFT : org.openqa.selenium.Keys [91]
    1178  aastore
    1179  dup
    1180  bipush 22
    1182  getstatic org.openqa.selenium.Keys.ARROW_LEFT : org.openqa.selenium.Keys [93]
    1185  aastore
    1186  dup
    1187  bipush 23
    1189  getstatic org.openqa.selenium.Keys.UP : org.openqa.selenium.Keys [96]
    1192  aastore
    1193  dup
    1194  bipush 24
    1196  getstatic org.openqa.selenium.Keys.ARROW_UP : org.openqa.selenium.Keys [98]
    1199  aastore
    1200  dup
    1201  bipush 25
    1203  getstatic org.openqa.selenium.Keys.RIGHT : org.openqa.selenium.Keys [101]
    1206  aastore
    1207  dup
    1208  bipush 26
    1210  getstatic org.openqa.selenium.Keys.ARROW_RIGHT : org.openqa.selenium.Keys [103]
    1213  aastore
    1214  dup
    1215  bipush 27
    1217  getstatic org.openqa.selenium.Keys.DOWN : org.openqa.selenium.Keys [106]
    1220  aastore
    1221  dup
    1222  bipush 28
    1224  getstatic org.openqa.selenium.Keys.ARROW_DOWN : org.openqa.selenium.Keys [108]
    1227  aastore
    1228  dup
    1229  bipush 29
    1231  getstatic org.openqa.selenium.Keys.INSERT : org.openqa.selenium.Keys [111]
    1234  aastore
    1235  dup
    1236  bipush 30
    1238  getstatic org.openqa.selenium.Keys.DELETE : org.openqa.selenium.Keys [114]
    1241  aastore
    1242  dup
    1243  bipush 31
    1245  getstatic org.openqa.selenium.Keys.SEMICOLON : org.openqa.selenium.Keys [117]
    1248  aastore
    1249  dup
    1250  bipush 32
    1252  getstatic org.openqa.selenium.Keys.EQUALS : org.openqa.selenium.Keys [120]
    1255  aastore
    1256  dup
    1257  bipush 33
    1259  getstatic org.openqa.selenium.Keys.NUMPAD0 : org.openqa.selenium.Keys [123]
    1262  aastore
    1263  dup
    1264  bipush 34
    1266  getstatic org.openqa.selenium.Keys.NUMPAD1 : org.openqa.selenium.Keys [126]
    1269  aastore
    1270  dup
    1271  bipush 35
    1273  getstatic org.openqa.selenium.Keys.NUMPAD2 : org.openqa.selenium.Keys [129]
    1276  aastore
    1277  dup
    1278  bipush 36
    1280  getstatic org.openqa.selenium.Keys.NUMPAD3 : org.openqa.selenium.Keys [132]
    1283  aastore
    1284  dup
    1285  bipush 37
    1287  getstatic org.openqa.selenium.Keys.NUMPAD4 : org.openqa.selenium.Keys [135]
    1290  aastore
    1291  dup
    1292  bipush 38
    1294  getstatic org.openqa.selenium.Keys.NUMPAD5 : org.openqa.selenium.Keys [138]
    1297  aastore
    1298  dup
    1299  bipush 39
    1301  getstatic org.openqa.selenium.Keys.NUMPAD6 : org.openqa.selenium.Keys [141]
    1304  aastore
    1305  dup
    1306  bipush 40
    1308  getstatic org.openqa.selenium.Keys.NUMPAD7 : org.openqa.selenium.Keys [144]
    1311  aastore
    1312  dup
    1313  bipush 41
    1315  getstatic org.openqa.selenium.Keys.NUMPAD8 : org.openqa.selenium.Keys [147]
    1318  aastore
    1319  dup
    1320  bipush 42
    1322  getstatic org.openqa.selenium.Keys.NUMPAD9 : org.openqa.selenium.Keys [150]
    1325  aastore
    1326  dup
    1327  bipush 43
    1329  getstatic org.openqa.selenium.Keys.MULTIPLY : org.openqa.selenium.Keys [153]
    1332  aastore
    1333  dup
    1334  bipush 44
    1336  getstatic org.openqa.selenium.Keys.ADD : org.openqa.selenium.Keys [156]
    1339  aastore
    1340  dup
    1341  bipush 45
    1343  getstatic org.openqa.selenium.Keys.SEPARATOR : org.openqa.selenium.Keys [159]
    1346  aastore
    1347  dup
    1348  bipush 46
    1350  getstatic org.openqa.selenium.Keys.SUBTRACT : org.openqa.selenium.Keys [162]
    1353  aastore
    1354  dup
    1355  bipush 47
    1357  getstatic org.openqa.selenium.Keys.DECIMAL : org.openqa.selenium.Keys [165]
    1360  aastore
    1361  dup
    1362  bipush 48
    1364  getstatic org.openqa.selenium.Keys.DIVIDE : org.openqa.selenium.Keys [168]
    1367  aastore
    1368  dup
    1369  bipush 49
    1371  getstatic org.openqa.selenium.Keys.F1 : org.openqa.selenium.Keys [171]
    1374  aastore
    1375  dup
    1376  bipush 50
    1378  getstatic org.openqa.selenium.Keys.F2 : org.openqa.selenium.Keys [174]
    1381  aastore
    1382  dup
    1383  bipush 51
    1385  getstatic org.openqa.selenium.Keys.F3 : org.openqa.selenium.Keys [177]
    1388  aastore
    1389  dup
    1390  bipush 52
    1392  getstatic org.openqa.selenium.Keys.F4 : org.openqa.selenium.Keys [180]
    1395  aastore
    1396  dup
    1397  bipush 53
    1399  getstatic org.openqa.selenium.Keys.F5 : org.openqa.selenium.Keys [183]
    1402  aastore
    1403  dup
    1404  bipush 54
    1406  getstatic org.openqa.selenium.Keys.F6 : org.openqa.selenium.Keys [186]
    1409  aastore
    1410  dup
    1411  bipush 55
    1413  getstatic org.openqa.selenium.Keys.F7 : org.openqa.selenium.Keys [189]
    1416  aastore
    1417  dup
    1418  bipush 56
    1420  getstatic org.openqa.selenium.Keys.F8 : org.openqa.selenium.Keys [192]
    1423  aastore
    1424  dup
    1425  bipush 57
    1427  getstatic org.openqa.selenium.Keys.F9 : org.openqa.selenium.Keys [195]
    1430  aastore
    1431  dup
    1432  bipush 58
    1434  getstatic org.openqa.selenium.Keys.F10 : org.openqa.selenium.Keys [198]
    1437  aastore
    1438  dup
    1439  bipush 59
    1441  getstatic org.openqa.selenium.Keys.F11 : org.openqa.selenium.Keys [201]
    1444  aastore
    1445  dup
    1446  bipush 60
    1448  getstatic org.openqa.selenium.Keys.F12 : org.openqa.selenium.Keys [204]
    1451  aastore
    1452  dup
    1453  bipush 61
    1455  getstatic org.openqa.selenium.Keys.META : org.openqa.selenium.Keys [207]
    1458  aastore
    1459  dup
    1460  bipush 62
    1462  getstatic org.openqa.selenium.Keys.COMMAND : org.openqa.selenium.Keys [209]
    1465  aastore
    1466  dup
    1467  bipush 63
    1469  getstatic org.openqa.selenium.Keys.ZENKAKU_HANKAKU : org.openqa.selenium.Keys [212]
    1472  aastore
    1473  putstatic org.openqa.selenium.Keys.$VALUES : org.openqa.selenium.Keys[] [1]
    1476  return
      Line numbers:
        [pc: 0, line: 30]
        [pc: 15, line: 31]
        [pc: 30, line: 32]
        [pc: 45, line: 33]
        [pc: 60, line: 34]
        [pc: 75, line: 35]
        [pc: 90, line: 36]
        [pc: 106, line: 37]
        [pc: 122, line: 38]
        [pc: 138, line: 39]
        [pc: 155, line: 40]
        [pc: 171, line: 41]
        [pc: 188, line: 42]
        [pc: 204, line: 43]
        [pc: 221, line: 44]
        [pc: 237, line: 45]
        [pc: 253, line: 46]
        [pc: 269, line: 47]
        [pc: 285, line: 48]
        [pc: 301, line: 49]
        [pc: 317, line: 50]
        [pc: 333, line: 51]
        [pc: 349, line: 52]
        [pc: 366, line: 53]
        [pc: 382, line: 54]
        [pc: 399, line: 55]
        [pc: 415, line: 56]
        [pc: 432, line: 57]
        [pc: 448, line: 58]
        [pc: 465, line: 59]
        [pc: 481, line: 60]
        [pc: 497, line: 61]
        [pc: 513, line: 62]
        [pc: 529, line: 65]
        [pc: 545, line: 66]
        [pc: 561, line: 67]
        [pc: 577, line: 68]
        [pc: 593, line: 69]
        [pc: 609, line: 70]
        [pc: 625, line: 71]
        [pc: 641, line: 72]
        [pc: 657, line: 73]
        [pc: 673, line: 74]
        [pc: 689, line: 75]
        [pc: 705, line: 76]
        [pc: 721, line: 77]
        [pc: 737, line: 78]
        [pc: 753, line: 79]
        [pc: 769, line: 80]
        [pc: 785, line: 83]
        [pc: 801, line: 84]
        [pc: 817, line: 85]
        [pc: 833, line: 86]
        [pc: 849, line: 87]
        [pc: 865, line: 88]
        [pc: 881, line: 89]
        [pc: 897, line: 90]
        [pc: 913, line: 91]
        [pc: 929, line: 92]
        [pc: 945, line: 93]
        [pc: 961, line: 94]
        [pc: 977, line: 96]
        [pc: 993, line: 97]
        [pc: 1010, line: 99]
        [pc: 1026, line: 28]
}